cvec/__init__.py
cvec/cvec.py
cvec/models/__init__.py
cvec/models/agent_post.py
cvec/models/eav_column.py
cvec/models/eav_filter.py
cvec/models/eav_table.py
cvec/models/metric.py
cvec/models/span.py
cvec/py.typed
cvec/utils/__init__.py
cvec/utils/arrow_converter.py
cvec-1.4.3.dist-info/METADATA
cvec-1.4.3.dist-info/WHEEL
cvec-1.4.3.dist-info/licenses/LICENSE
cvec-1.4.3.dist-info/RECORD
