Metadata-Version: 2.4
Name: cvec
Version: 1.4.3
Summary: SDK for CVector Energy
License-Expression: MIT
License-File: LICENSE
Author: CVector
Author-email: support@cvector.energy
Requires-Python: >=3.10
Classifier: License :: OSI Approved :: MIT License
Classifier: Operating System :: OS Independent
Classifier: Programming Language :: Python :: 3
Classifier: Intended Audience :: Developers
Classifier: Programming Language :: Python :: 3.10
Classifier: Programming Language :: Python :: 3.11
Classifier: Programming Language :: Python :: 3.12
Classifier: Programming Language :: Python :: 3.13
Classifier: Programming Language :: Python :: 3.14
Requires-Dist: pyarrow (>=22.0.0)
Requires-Dist: pydantic (>=2.12.0)
